setup.cfg
setup.py
hap/__init__.py
hap/__main__.py
hap/bootstrap.py
hap/cache.py
hap/field.py
hap/log.py
hap/parser.py
hap/reader.py
hap/shell.py
hap/util.py
hap/writer.py
hap.egg-info/PKG-INFO
hap.egg-info/SOURCES.txt
hap.egg-info/dependency_links.txt
hap.egg-info/entry_points.txt
hap.egg-info/requires.txt
hap.egg-info/top_level.txt