Metadata-Version: 1.1
Name: hap
Version: 1.2.3
Summary: A simple HTML scraping tool
Home-page: https://github.com/lexndru/hap
Author: Alexandru Catrina
Author-email: alex@codeissues.net
License: MIT
Download-URL: https://github.com/lexndru/hap/archive/v1.2.3.tar.gz
Keywords: html,scraping,crawler,tool,hap
Platform: UNKNOWN
Classifier: Development Status :: 5 - Production/Stable
Classifier: Intended Audience :: Developers
Classifier: Intended Audience :: End Users/Desktop
Classifier: Topic :: Internet :: WWW/HTTP
Classifier: Topic :: Text Processing :: Markup :: HTML
Classifier: License :: OSI Approved :: MIT License
Classifier: Programming Language :: Python :: 2.7
